cocontents/__init__.py
cocontents/hello.py
vidcontents-0.0.1.dist-info/LICENSE
vidcontents-0.0.1.dist-info/METADATA
vidcontents-0.0.1.dist-info/WHEEL
vidcontents-0.0.1.dist-info/top_level.txt
vidcontents-0.0.1.dist-info/RECORD
